{
    "default_acceleration": "3000",
    "default_jerk": "1",
    "from": "User",
    "inherits": "0.20mm Standard @MyKlipper",
    "inner_wall_acceleration": "3000",
    "inner_wall_jerk": "1",
    "inner_wall_line_width": "0.5",
    "inner_wall_speed": "100",
    "internal_solid_infill_line_width": "0.5",
    "internal_solid_infill_speed": "180",
    "line_width": "0.5",
    "name": "0.20mm Standard @LARETC",
    "outer_wall_jerk": "1",
    "outer_wall_line_width": "0.5",
    "outer_wall_speed": "100",
    "print_settings_id": "0.20mm Standard @LARETC",
    "seam_gap": "45%",
    "sparse_infill_line_width": "0.5",
    "sparse_infill_speed": "180",
    "support_line_width": "0.5",
    "top_surface_line_width": "0.5",
    "travel_acceleration": "3000",
    "version": "1.6.1.0",
    "wall_generator": "classic",
    "wall_sequence": "outer wall/inner wall",
    "wipe_on_loops": "1"
}
